pynrc/__init__.py
pynrc/detops.py
pynrc/logging_utils.py
pynrc/nb_funcs.py
pynrc/nrc_utils.py
pynrc/obs_nircam.py
pynrc/opds.py
pynrc/pynrc_core.py
pynrc/speckle_noise.py
pynrc/testing.py
pynrc/version.py
pynrc/maths/__init__.py
pynrc/maths/_robust.py
pynrc/maths/coords.py
pynrc/maths/fast_poly.py
pynrc/maths/image_manip.py
pynrc/reduce/__init__.py
pynrc/reduce/analysis.py
pynrc/reduce/calib.py
pynrc/reduce/ddit.py
pynrc/reduce/nmf.py
pynrc/reduce/pca.py
pynrc/reduce/ref_pixels.py
pynrc/simul/__init__.py
pynrc/simul/_nghxrg.py
pynrc/simul/apt.py
pynrc/simul/dms.py
pynrc/simul/ngNRC.py
pynrc/simul/skyvec2ins.py
pynrc-2.0.1.dist-info/LICENSE
pynrc-2.0.1.dist-info/METADATA
pynrc-2.0.1.dist-info/WHEEL
pynrc-2.0.1.dist-info/top_level.txt
pynrc-2.0.1.dist-info/RECORD
