Metadata-Version: 2.1
Name: pynrc
Version: 2.0.1
Summary: JWST NIRCam ETC and Simulator
Home-page: https://pynrc.readthedocs.io
Author: Jarron Leisenring
Author-email: jarronl@arizona.edu
License: MIT license
Keywords: jwst nircam etc simulator
Classifier: Development Status :: 5 - Production/Stable
Classifier: Intended Audience :: Developers
Classifier: Topic :: Scientific/Engineering :: Astronomy
Classifier: License :: OSI Approved :: MIT License
Classifier: Programming Language :: Python :: 3
Classifier: Programming Language :: Python :: 3.10
Classifier: Programming Language :: Python :: 3.11
License-File: LICENSE
Requires-Dist: tqdm (>4)
Requires-Dist: webbpsf-ext (>=2.0.0)
Requires-Dist: astroquery (>=0.4.6)
Requires-Dist: jwst
Provides-Extra: docs
Requires-Dist: docutils (==0.18) ; extra == 'docs'
Requires-Dist: sphinx (>=3.4.1) ; extra == 'docs'
